wordpress_markdown_blog_loader/__init__.py
wordpress_markdown_blog_loader/__main__.py
wordpress_markdown_blog_loader/api.py
wordpress_markdown_blog_loader/blog.py
wordpress_markdown_blog_loader/check_links.py
wordpress_markdown_blog_loader/download.py
wordpress_markdown_blog_loader/html_to_gutenberg.py
wordpress_markdown_blog_loader/name_to_email.py
wordpress_markdown_blog_loader/new.py
wordpress_markdown_blog_loader/remove_newlines.py
wordpress_markdown_blog_loader/upload.py
wordpress_markdown_blog_loader-1.7.0.dist-info/licenses/LICENSE
wordpress_markdown_blog_loader-1.7.0.dist-info/METADATA
wordpress_markdown_blog_loader-1.7.0.dist-info/WHEEL
wordpress_markdown_blog_loader-1.7.0.dist-info/entry_points.txt
wordpress_markdown_blog_loader-1.7.0.dist-info/top_level.txt
wordpress_markdown_blog_loader-1.7.0.dist-info/RECORD
