Metadata-Version: 2.4
Name: wordpress-markdown-blog-loader
Version: 1.7.0
Summary: load markdown blogs into wordpress
Author-email: Mark van Holsteijn <markvanholsteijn@binx.io>
License: APL2
Project-URL: Homepage, https://github.com/binxio/wordpress-markdown-blog-loader
Classifier: Development Status :: 4 - Beta
Classifier: Environment :: Console
Classifier: Intended Audience :: Developers
Classifier: License :: OSI Approved :: BSD License
Classifier: Operating System :: POSIX
Classifier: Operating System :: MacOS
Classifier: Operating System :: Unix
Classifier: Operating System :: Microsoft :: Windows
Classifier: Programming Language :: Python :: 3
Classifier: Topic :: Software Development :: Libraries :: Python Modules
License-File: LICENSE
Requires-Dist: requests
Requires-Dist: markdown
Requires-Dist: python-frontmatter
Requires-Dist: click
Requires-Dist: pytz
Requires-Dist: Pillow
Requires-Dist: binx-og-image-generator>=1.2.6
Requires-Dist: markdownify
Requires-Dist: bs4
Requires-Dist: html5lib
Requires-Dist: lxml
Requires-Dist: python-slugify
Requires-Dist: unidecode
Requires-Dist: stopwords
Provides-Extra: testing
Requires-Dist: requests; extra == "testing"
Requires-Dist: markdown; extra == "testing"
Requires-Dist: python-frontmatter; extra == "testing"
Requires-Dist: click; extra == "testing"
Requires-Dist: pytz; extra == "testing"
Requires-Dist: Pillow; extra == "testing"
Requires-Dist: binx-og-image-generator>=1.2.6; extra == "testing"
Requires-Dist: markdownify; extra == "testing"
Requires-Dist: bs4; extra == "testing"
Requires-Dist: html5lib; extra == "testing"
Requires-Dist: lxml; extra == "testing"
Requires-Dist: python-slugify; extra == "testing"
Requires-Dist: pytest; extra == "testing"
Requires-Dist: unidecode; extra == "testing"
Requires-Dist: stopwords; extra == "testing"
Dynamic: license-file
